MANIFEST.in
README.md
fuckit.py
setup.py
fuckit.egg-info/PKG-INFO
fuckit.egg-info/SOURCES.txt
fuckit.egg-info/dependency_links.txt
fuckit.egg-info/requires.txt
fuckit.egg-info/top_level.txt