Metadata-Version: 1.1
Name: fuckit
Version: 1.0.1
Summary: The Python Error Steamroller
Home-page: https://github.com/ajalt/fuckitpy
Author: AJ Alt
Author-email: UNKNOWN
License: WTFPL
Platform: any
Classifier: Programming Language :: Python :: 2 :: Only
Classifier: Development Status :: 4 - Beta
Classifier: Natural Language :: English
Classifier: Environment :: Console
Classifier: Intended Audience :: Developers
Classifier: Operating System :: OS Independent
Classifier: Topic :: Software Development :: Libraries :: Python Modules
